models/__init__.py
models/datafile/__init__.py
models/sentence/__init__.py
models/tasks/__init__.py
models/tasks/datafile/__init__.py
models/tasks/datafile/upload.py
models/tasks/sentence/__init__.py
models/tasks/sentence/save.py
models/tasks/wordcloud/__init__.py
models/tasks/wordcloud/create.py
models/user/__init__.py
models/wordcloud/__init__.py
nleaser_config/__init__.py
sources/__init__.py
sources/authentication/__init__.py
sources/authentication/services.py
sources/datafile/__init__.py
sources/datafile/exceptions.py
sources/datafile/services.py
sources/datafile/util.py
sources/logger/__init__.py
sources/nlp/__init__.py
sources/nlp/preprocessing/__init__.py
sources/nlp/tfidf/__init__.py
sources/nlp/tfidf/wordcloud/__init__.py
sources/rabbit/__init__.py
sources/rabbit/consumer.py
sources/rabbit/producer.py
sources/sentences/__init__.py
sources/sentences/services.py
sources/tasks/__init__.py
sources/tasks/datafile/__init__.py
sources/tasks/datafile/upload.py
sources/tasks/sentences/__init__.py
sources/tasks/sentences/save.py
sources/tasks/wordcloud/__init__.py
sources/tasks/wordcloud/create.py
sources/user/__init__.py
sources/wordcloud/__init__.py
sources/wordcloud/services.py
workers/sentence_import/__init__.py
workers/sentence_import/__main__.py
sentence_import_worker_NLEaser-0.4.0.dist-info/METADATA
sentence_import_worker_NLEaser-0.4.0.dist-info/WHEEL
sentence_import_worker_NLEaser-0.4.0.dist-info/top_level.txt
sentence_import_worker_NLEaser-0.4.0.dist-info/RECORD
